ruxitools/__init__.py
ruxitools/xydb.py
ruxitools/gitpath/__init__.py
ruxitools-0.2.7.dist-info/DESCRIPTION.rst
ruxitools-0.2.7.dist-info/METADATA
ruxitools-0.2.7.dist-info/RECORD
ruxitools-0.2.7.dist-info/WHEEL
ruxitools-0.2.7.dist-info/metadata.json
ruxitools-0.2.7.dist-info/top_level.txt
