Metadata-Version: 2.0
Name: ruxitools
Version: 0.2.7
Summary: Misc general use functions. XyDB: container fo intermediate data. 
Home-page: http://github.com/ruxi/tools
Author: ruxi
Author-email: ruxi.github@gmail.com
License: MIT
Keywords: ruxi tools ruxitools xydb intermediate data containers
Platform: UNKNOWN
Classifier: Programming Language :: Python
Classifier: Development Status :: 3 - Alpha
Classifier: Intended Audience :: Developers
Classifier: Intended Audience :: Science/Research
Classifier: License :: OSI Approved :: MIT License
Classifier: Natural Language :: English
Classifier: Operating System :: Unix
Classifier: Programming Language :: Python :: 3 :: Only
